mbtools/__init__.py
mbtools-0.1.1.dist-info/LICENCE
mbtools-0.1.1.dist-info/METADATA
mbtools-0.1.1.dist-info/WHEEL
mbtools-0.1.1.dist-info/top_level.txt
mbtools-0.1.1.dist-info/RECORD
