Metadata-Version: 2.1
Name: mbtools
Version: 0.1.1
Summary: Project that offer utility functions to treat strings, numbers, files etc.
Home-page: https://github.com/misaelbarreto/mbtools
Author: Misael Barreto de Queiroz
Author-email: misaelbarreto@gmail.com
License: BSD License
Platform: UNKNOWN
Classifier: Programming Language :: Python :: 3
Classifier: License :: OSI Approved :: BSD License
Classifier: Operating System :: OS Independent
